[1,["5fKxxTDj1MCYsc7b1iF3ua"],["_textureSetter"],["cc.SpriteFrame"],0,[[[{"name":"ç‚¸ĺĽą4","rect":[1200,0,400,400],"offset":[0,0],"originalSize":[400,400],"capInsets":[0,0,0,0]}],[0],0,[0],[0],[0]],[[{"name":"ç‚¸ĺĽą14","rect":[1200,800,400,400],"offset":[0,0],"originalSize":[400,400],"capInsets":[0,0,0,0]}],[0],0,[0],[0],[0]],[[{"name":"ç‚¸ĺĽą3","rect":[800,0,400,400],"offset":[0,0],"originalSize":[400,400],"capInsets":[0,0,0,0]}],[0],0,[0],[0],[0]],[[{"name":"ç‚¸ĺĽą13","rect":[800,800,400,400],"offset":[0,0],"originalSize":[400,400],"capInsets":[0,0,0,0]}],[0],0,[0],[0],[0]],[[{"name":"ç‚¸ĺĽą18","rect":[800,1200,400,400],"offset":[0,0],"originalSize":[400,400],"capInsets":[0,0,0,0]}],[0],0,[0],[0],[0]],[[{"name":"ç‚¸ĺĽą22","rect":[400,1600,400,400],"offset":[0,0],"originalSize":[400,400],"capInsets":[0,0,0,0]}],[0],0,[0],[0],[0]],[[{"name":"ç‚¸ĺĽą17","rect":[400,1200,400,400],"offset":[0,0],"originalSize":[400,400],"capInsets":[0,0,0,0]}],[0],0,[0],[0],[0]],[[{"name":"ç‚¸ĺĽą2","rect":[400,0,400,400],"offset":[0,0],"originalSize":[400,400],"capInsets":[0,0,0,0]}],[0],0,[0],[0],[0]],[[{"name":"ç‚¸ĺĽą12","rect":[400,800,400,400],"offset":[0,0],"originalSize":[400,400],"capInsets":[0,0,0,0]}],[0],0,[0],[0],[0]],[[{"name":"ç‚¸ĺĽą20","rect":[1600,1200,400,400],"offset":[0,0],"originalSize":[400,400],"capInsets":[0,0,0,0]}],[0],0,[0],[0],[0]],[[{"name":"ç‚¸ĺĽą11","rect":[0,800,400,400],"offset":[0,0],"originalSize":[400,400],"capInsets":[0,0,0,0]}],[0],0,[0],[0],[0]],[[{"name":"ç‚¸ĺĽą5","rect":[1600,0,400,400],"offset":[0,0],"originalSize":[400,400],"capInsets":[0,0,0,0]}],[0],0,[0],[0],[0]],[[{"name":"ç‚¸ĺĽą6","rect":[0,400,400,400],"offset":[0,0],"originalSize":[400,400],"capInsets":[0,0,0,0]}],[0],0,[0],[0],[0]],[[{"name":"ç‚¸ĺĽą19","rect":[1200,1200,400,400],"offset":[0,0],"originalSize":[400,400],"capInsets":[0,0,0,0]}],[0],0,[0],[0],[0]],[[{"name":"ç‚¸ĺĽą21","rect":[0,1600,400,400],"offset":[0,0],"originalSize":[400,400],"capInsets":[0,0,0,0]}],[0],0,[0],[0],[0]],[[{"name":"ç‚¸ĺĽą8","rect":[800,400,400,400],"offset":[0,0],"originalSize":[400,400],"capInsets":[0,0,0,0]}],[0],0,[0],[0],[0]],[[{"name":"ç‚¸ĺĽą16","rect":[0,1200,400,400],"offset":[0,0],"originalSize":[400,400],"capInsets":[0,0,0,0]}],[0],0,[0],[0],[0]],[[{"name":"ç‚¸ĺĽą1","rect":[0,0,400,400],"offset":[0,0],"originalSize":[400,400],"capInsets":[0,0,0,0]}],[0],0,[0],[0],[0]],[[{"name":"ç‚¸ĺĽą10","rect":[1600,400,400,400],"offset":[0,0],"originalSize":[400,400],"capInsets":[0,0,0,0]}],[0],0,[0],[0],[0]],[[{"name":"ç‚¸ĺĽą9","rect":[1200,400,400,400],"offset":[0,0],"originalSize":[400,400],"capInsets":[0,0,0,0]}],[0],0,[0],[0],[0]],[[{"name":"ç‚¸ĺĽą15","rect":[1600,800,400,400],"offset":[0,0],"originalSize":[400,400],"capInsets":[0,0,0,0]}],[0],0,[0],[0],[0]],[[{"name":"ç‚¸ĺĽą7","rect":[400,400,400,400],"offset":[0,0],"originalSize":[400,400],"capInsets":[0,0,0,0]}],[0],0,[0],[0],[0]]]]